truhanen/stuiplot/__init__.py
truhanen/stuiplot/stuiplot.py
truhanen.stuiplot-0.1.0.dist-info/entry_points.txt
truhanen.stuiplot-0.1.0.dist-info/WHEEL
truhanen.stuiplot-0.1.0.dist-info/METADATA
truhanen.stuiplot-0.1.0.dist-info/RECORD
