Metadata-Version: 2.1
Name: truhanen.stuiplot
Version: 0.1.0
Summary: Script for plotting s-tui logs
Home-page: https://github.com/truhanen/stuiplot
License: MIT
Author: Tuukka Ruhanen
Author-email: tuukka.t.ruhanen@gmail.com
Requires-Python: >=3.8
Classifier: License :: OSI Approved :: MIT License
Classifier: Programming Language :: Python :: 3
Classifier: Programming Language :: Python :: 3.10
Classifier: Programming Language :: Python :: 3.8
Classifier: Programming Language :: Python :: 3.9
Classifier: Topic :: Utilities
Requires-Dist: matplotlib (>=3.4.0)
Requires-Dist: numpy (>=1.21.0)
Requires-Dist: pandas (>=1.3.0)
